LICENSE
MANIFEST.in
README.rst
setup.py
actionslog/__init__.py
actionslog/admin.py
actionslog/apps.py
actionslog/diff.py
actionslog/forms.py
actionslog/middleware.py
actionslog/models.py
actionslog/receivers.py
actionslog/registry.py
actionslog/settings.py
actionslog/signals.py
actionslog/migrations/0001_initial.py
actionslog/migrations/0002_auto_20181211_1518.py
actionslog/migrations/__init__.py
django_actions_logger.egg-info/PKG-INFO
django_actions_logger.egg-info/SOURCES.txt
django_actions_logger.egg-info/dependency_links.txt
django_actions_logger.egg-info/not-zip-safe
django_actions_logger.egg-info/requires.txt
django_actions_logger.egg-info/top_level.txt