Metadata-Version: 1.1
Name: django-actions-logger
Version: 0.2.2
Summary: A Django app that keeps a log of user actions or changes in objects
Home-page: https://github.com/shtalinberg/django-actions-logger
Author: Oleksandr Shtalinberg
Author-email: shtalinberg@ukr.net
License: MIT
Keywords: django actions log action logger
Platform: UNKNOWN
Classifier: Development Status :: 5 - Production/Stable
Classifier: Environment :: Web Environment
Classifier: Framework :: Django
Classifier: Intended Audience :: Developers
Classifier: License :: OSI Approved :: MIT License
Classifier: Operating System :: OS Independent
Classifier: Programming Language :: Python
Classifier: Programming Language :: Python :: 3
Classifier: Topic :: Utilities
